[
    {
        "comment_rate": "2",
        "title": "A股异动 | 三环集团大跌11% 前三季度增收不增利",
        "publish_time": "2023-10-26 10:25",
        "comments": [
            "2023-11-14 11:14:51 这年头倒闭公司太多了，三环有这样的成绩已经不错了！",
            "2023-10-26 10:40:35 危言耸听的标题"
        ]
    },
    {
        "comment_rate": "1",
        "title": "三环集团(300408.SZ)：车规级MLCC产品已通过车规体系认证 部分常规容量规格已开始导入汽车供应链",
        "publish_time": "2023-05-17 14:50",
        "comments": [
            "2023-06-05 12:03:51 今天收盘31"
        ]
    },
    {
        "comment_rate": "2",
        "title": "最高涨幅40%，连跌14月的MLCC迎来拐点？",
        "publish_time": "2023-05-10 14:15",
        "comments": [
            "2023-05-10 15:15:09 这么大的利好明天破28需要怀疑吗？",
            "2023-05-10 14:19:09 滚，跌出了"
        ]
    },
    {
        "comment_rate": "10",
        "title": "东吴证券：MLCC供给端出清 行业处于周期反转前夜",
        "publish_time": "2023-04-14 07:50",
        "comments": [
            "2023-04-22 10:26:28 你是懂“反转”的",
            "2023-04-19 14:37:21 研报一出，又要哀鸿遍野了",
            "2023-04-19 14:06:26 死垃圾",
            "2023-04-19 13:58:37 MD",
            "2023-04-17 22:21:48 写这个的真泥M缺德！",
            "2023-04-17 22:11:09 太厉害了，股价天天跌，股评天天有！！",
            "2023-04-17 14:26:23 忽悠。主力出货，叫散户接盘",
            "2023-04-17 11:01:39 ",
            "2023-04-17 09:51:46 ",
            "2023-04-15 15:19:45 前夜？等反转了再说！鬼知道这个前夜有多久！存储行业去年也是这么说的，4月份了还是去年的那个说辞！"
        ]
    },
    {
        "comment_rate": "4",
        "title": "MLCC涨价！又一MLCC龙头透露：部分料号已涨价！",
        "publish_time": "2023-04-13 12:18",
        "comments": [
            "2023-04-17 14:27:34 忽悠。两股全部下跌",
            "2023-04-14 07:41:24 产品涨价，股价下跌，你厉害",
            "2023-04-14 07:10:49 6",
            "2023-04-13 12:38:45 那为啥跌"
        ]
    },
    {
        "comment_rate": "5",
        "title": "华西证券：AlN应用性能出众 国产替代机遇显著",
        "publish_time": "2023-04-04 14:41",
        "comments": [
            "2023-04-28 14:56:47 潜力品类",
            "2023-04-07 12:10:00 Ai芯片上游关键材料",
            "2023-04-05 23:36:08 国产替代就是最重要达到的目标 所有国产替代的市值未来都会有所增长 中国NB",
            "2023-04-05 09:58:30 人工智能需要这些东西吗？",
            "2023-04-06 17:16:48 要做国产化的只有人工智能？"
        ]
    },
    {
        "comment_rate": "2",
        "title": "任正非重申“不造车”，瞄准产业链核心持续深耕，华为题材多股涨停！",
        "publish_time": "2023-04-03 14:28",
        "comments": [
            "2023-04-06 07:05:45 华为80%光通信器件都是光迅科技提供，做为国内自主研发光芯片第一股，恰逢盘古大模型上市之际即将爆发，光迅一季度业绩也将爆发",
            "2023-04-03 17:25:27 伤及赛力斯"
        ]
    },
    {
        "comment_rate": "2",
        "title": "安信证券：5G换机与汽车电动化驱动成长 MLCC需求复苏或于23Q2-Q3左右体现",
        "publish_time": "2023-03-27 15:05",
        "comments": [
            "2023-12-09 17:41:03 准过吗？",
            "2023-12-09 13:34:59 行业跟踪"
        ]
    },
    {
        "comment_rate": "6",
        "title": "国金证券：被动元器件景气度已见底 看好汽车、工业领域机会",
        "publish_time": "2023-03-15 09:48",
        "comments": [
            "2023-04-03 19:30:31 顺络电子(002138.SZ)看好长期价值",
            "2023-04-03 18:31:39 泰晶对比其他公司，太便宜，疫情后修复，不到5o元不能体现公司的价值",
            "2023-04-03 17:37:52 值得跟进！",
            "2023-03-16 13:33:54 加油干！",
            "2023-03-16 13:33:27 ",
            "2023-03-16 14:30:33 好股不怕跌，买进"
        ]
    },
    {
        "comment_rate": "1",
        "title": "聚焦经济新动能|发电能耗降一半 SOFC大规模商用“燃点”临近",
        "publish_time": "2023-03-04 08:20",
        "comments": [
            "2023-03-04 09:13:43 没看见三环尾盘被疯狂砸吗？半导体利好都被压一整天最后收盘还打砸，这个sofc算啥，小众化的东西成不了气候，发再多作文也是跌不停的命！唉！"
        ]
    },
    {
        "comment_rate": "1",
        "title": "受益汽车智能化发展，千亿市场爆发，车规级MLCC产业迎来新增量市场",
        "publish_time": "2022-12-29 09:35",
        "comments": [
            "2022-12-30 01:02:25 正常的股票靠大市和庄，散户太多庄家资金雄厚才能操作，否则韮菜死猪不怕开水烫.这票只能半生不死"
        ]
    },
    {
        "comment_rate": "9",
        "title": "三环集团遭遇周期寒流",
        "publish_time": "2022-11-07 20:55",
        "comments": [
            "2022-12-18 11:11:50 有个问题想咨询一下，三环集团做的是中低端业务，为何毛利率高于高于海外中高端同行，这有点不符合常识啊。就如中芯国际毛利率高于台积电一样不可思议啊！有哪位大神能解答一下吗？",
            "2022-12-18 20:19:20 我就是冲MLCC来，不做这个就算了。",
            "2022-12-18 18:57:14 三环只做MLCC么？",
            "2022-12-01 14:15:30 三环只做MLCC么？",
            "2022-11-07 22:53:48 只要会上网都知道MLCC中高端产品95%在外企手中！",
            "2022-11-09 14:28:12 现在股价已早表现出来了",
            "2022-11-09 11:31:17 介绍得还算不错，中规中矩"
        ]
    },
    {
        "comment_rate": "3",
        "title": "第四季MLCC需求持续疲弱，然中国现货市场库存下降，有助消费级价格跌势趋缓",
        "publish_time": "2022-11-07 14:05",
        "comments": [
            "2022-11-07 16:03:26 大哥，你就别在这唱空了，兄弟们好多都套着呢？人家财务具体怎么样跟你有啥关系",
            "2022-11-07 15:20:32 唱空的又来了",
            "2022-11-07 15:03:50 已阅"
        ]
    },
    {
        "comment_rate": "2",
        "title": "MLCC市场持续低迷 三环集团扣非净利连续大降",
        "publish_time": "2022-10-27 16:21",
        "comments": [
            "2022-11-17 11:14:51 涨跌和目前业绩有关系吗？韭菜",
            "2022-10-28 22:10:07 要筹码吓散户伎俩，也不得玩这种死票，除非放大换手率。"
        ]
    },
    {
        "comment_rate": "2",
        "title": "三环集团：已成为全球SOFC电解质隔膜、SOFC单电池的主要供应商",
        "publish_time": "2022-09-21 20:28",
        "comments": [
            "2022-10-10 09:41:20 工厂处于半停厂状态了，工人一个月一千多元，不哓得你天天在吹啥",
            "2022-09-22 13:45:33 股价一路下跌"
        ]
    },
    {
        "comment_rate": "1",
        "title": "芯报丨JLSemi景略半导体完成近亿美元C轮融资",
        "publish_time": "2022-07-10 20:34",
        "comments": [
            "2022-07-11 08:53:46 支持"
        ]
    },
    {
        "comment_rate": "1",
        "title": "股价半年暴跌34%，高瓴、诺德都被套牢！三环集团为何还受青睐？",
        "publish_time": "2022-06-20 13:31",
        "comments": [
            "2022-06-20 17:01:20 高瓴这些大机构这么容易被割韭菜啊？比散户不如？"
        ]
    },
    {
        "comment_rate": "8",
        "title": "氢能动态 | 恒力石化：500万吨/年煤化工包括30 万吨纯氢产能；三环集团：固体氧化物燃料电池电堆已完成课题综合绩效评价",
        "publish_time": "2022-05-11 17:26",
        "comments": [
            "2022-05-13 16:36:59 公司概念很快就会有氢能源，这样可以提升公司的市盈率，有望提升股价。",
            "2022-05-13 16:26:43 氢20万吨，所占比重是不是少点？",
            "2022-05-13 14:01:24 垃圾公司 实控人 没有道德 赶紧跌停。。。",
            "2022-05-13 13:59:28 新能源哦",
            "2022-05-13 13:59:03 新能源",
            "2022-05-13 16:27:03 氢20万吨，所占比重是不是少点？",
            "2022-05-11 17:46:04 大利好",
            "2022-05-13 16:26:55 氢20万吨，所占比重是不是少点？"
        ]
    },
    {
        "comment_rate": "3",
        "title": "三环集团：目前公司已能生产多种规格MLCC产品",
        "publish_time": "2022-05-09 19:43",
        "comments": [
            "2022-05-13 14:47:52 ",
            "2022-05-13 13:59:15 ",
            "2022-05-11 08:11:33 "
        ]
    },
    {
        "comment_rate": "1",
        "title": "三环集团Q1实现营收14.02亿元，净利润同比增长1.59%",
        "publish_time": "2022-04-29 19:41",
        "comments": [
            "2022-05-13 14:03:01 "
        ]
    },
    {
        "comment_rate": "1",
        "title": "电子元件及材料订单大增，三环集团2021年营收同比增长55.69%",
        "publish_time": "2022-04-24 21:04",
        "comments": [
            "2022-04-24 22:28:10 明天涨停"
        ]
    },
    {
        "comment_rate": "2",
        "title": "广东打造氢能产业发展高地：冲破制、储、运环节堵点",
        "publish_time": "2022-04-18 11:59",
        "comments": [
            "2022-05-13 13:41:27 利好sofc",
            "2022-04-18 13:16:09 21世纪经济报是个什么报纸？整天胡说八道"
        ]
    },
    {
        "comment_rate": "5",
        "title": "股民惊呆：最惨巨亏57%！投资大佬葛卫东突然栽了！更有高瓴、景林、王亚伟等私募大佬也套惨了...",
        "publish_time": "2022-04-16 15:22",
        "comments": [
            "2022-04-16 21:22:12 子越多总结字越少：跑",
            "2022-04-16 16:46:24 我20年炒股经验：买价低股（黑马往往在低价股产生）、己长横盘（庄收货到尾声）、有业绩（被套能解套）、不追高（防被套或见好就收），从不买高价股（如下跌空间大），赚钱取出（保存果实、否则不算赚钱）等等，获利卖出寻找另一长横盘低点股，再耐心持有，但能做到这几点很少，大都没耐心与被庄振旦洗盘洗出去了，看好就坚定意志，不为其它股上涨而动摇信心，大都赚钱，近十年收益不错。",
            "2022-04-16 23:07:39 你解释一下茅台，云南白药",
            "2022-04-16 19:21:44 高手！",
            "2022-04-16 16:08:40 那里来回那里去。。"
        ]
    }
]